[
 {
  "id": "amd-rx-6400",
  "brand": "AMD",
  "name": "AMD RX 6400",
  "index": 28.8,
  "vramGb": 4,
  "price": 170.0,
  "tdp": null,
  "priceMin": 170.0,
  "prices": [
   {
    "shop": "bpm-power.com",
    "price": 170.0,
    "currency": "EUR",
    "url": "https://www.gputracker.eu/si-click/1/1542674/scheda-video-amd-xfx-radeon-rx6400-swft105-gaming-",
    "inStock": true,
    "lastSeen": "2026-07-06T12:02:39Z",
    "product": "Scheda Video Amd Xfx RADEON RX6400 SWFT105 GAMING DP/H SPEEDSTER SWFT105 RADEON RX 6400 Gaming 4GB [RX-64XL4SFG2]"
   },
   {
    "shop": "jacob.de",
    "price": 183.0,
    "currency": "EUR",
    "url": "https://www.gputracker.eu/si-click/1/1526235/xfx-speedster-swft105-radeon-rx-6400-grafikkarte-4",
    "inStock": true,
    "lastSeen": "2026-07-06T12:02:39Z",
    "product": "XFX Speedster SWFT105 Radeon RX 6400 Grafikkarte 4GB GDDR6 Low-Profile (RX-64XL4SFG2)"
   },
   {
    "shop": "amazon.fr",
    "price": 193.0,
    "currency": "EUR",
    "url": "https://www.gputracker.eu/si-click/1/3812087/xfx-speedster-swft105-radeon-rx-6400-gaming-carte-",
    "inStock": true,
    "lastSeen": "2026-07-06T12:02:39Z",
    "product": "XFX Speedster SWFT105 Radeon RX 6400 Gaming Carte Graphique avec 4GB GDDR6, AMD RDNA™ 2 (RX-64XL4SFG2)"
   },
   {
    "shop": "topbiz.fr",
    "price": 203.0,
    "currency": "EUR",
    "url": "https://www.gputracker.eu/si-click/1/4392753/xfx-rx-64xl4sfg2-carte-graphique-amd-radeon-rx-640",
    "inStock": true,
    "lastSeen": "2026-07-06T12:02:39Z",
    "product": "XFX RX-64XL4SFG2 carte graphique AMD Radeon RX 6400 4 Go GDDR6"
   },
   {
    "shop": "openit.be",
    "price": 240.0,
    "currency": "EUR",
    "url": "https://www.gputracker.eu/si-click/1/3193632/hp-carte-graphique-amd-radeon-rx-6400-4-go-dphdmi-",
    "inStock": false,
    "lastSeen": "2026-07-06T12:02:39Z",
    "product": "HP Carte graphique AMD Radeon RX 6400 4 Go DP+HDMI (6Q3U4AA)"
   },
   {
    "shop": "bpm-power.com",
    "price": 295.0,
    "currency": "EUR",
    "url": "https://www.gputracker.eu/si-click/1/2175909/scheda-video-amd-hp-radeon-rx-6400-4gb-gddr6-6q3u4",
    "inStock": true,
    "lastSeen": "2026-07-06T12:02:39Z",
    "product": "Scheda Video Amd Hp Radeon RX 6400 4GB GDDR6 [6Q3U4AA]"
   }
  ],
  "image": "images/amd-rx-6400.png",
  "sourceUrl": "https://www.gputracker.eu/en/search/category/1/graphics-cards/facet/2/graphics-chip/amd-rx-6400",
  "lastUpdated": "2026-07-06T12:02:39Z",
  "imageSource": "https://img-cdn-aws.gputracker.eu/fit-in/150x150/products/084/0191/0840191500169.png?signature=c66bf449db7f6b521b79832b25bec18e3385a4d8a85efab0355eafc3ab2a1517"
 },
 {
  "id": "amd-rx-7600",
  "brand": "AMD",
  "name": "AMD RX 7600",
  "index": 61.3,
  "vramGb": 8,
  "price": 253.0,
  "tdp": 165,
  "priceMin": 253.0,
  "prices": [
   {
    "shop": "amazon.de",
    "price": 253.0,
    "currency": "EUR",
    "url": "https://www.gputracker.eu/si-click/1/3470730/asus-dual-radeon-rx-7600-evo-oc-edition-8gb-gddr6-",
    "inStock": true,
    "lastSeen": "2026-07-06T12:02:39Z",
    "product": "ASUS Dual Radeon RX 7600 EVO OC Edition 8GB GDDR6 Gaming Graphics Card (AMD Radeon RX7600, PCIe 4.0, 1x HDMI 2.1, 3X DisplayPort 1.4a)"
   },
   {
    "shop": "grosbill.com",
    "price": 275.0,
    "currency": "EUR",
    "url": "https://www.gputracker.eu/si-click/1/3041979/asus-radeon-dual-rx-7600-o8g-v2-seconde-vie-parfai",
    "inStock": false,
    "lastSeen": "2026-07-06T12:02:39Z",
    "product": "Asus Radeon DUAL RX 7600 O8G V2-Seconde Vie-Parfait Etat"
   },
   {
    "shop": "cybertek.fr",
    "price": 275.0,
    "currency": "EUR",
    "url": "https://www.gputracker.eu/si-click/1/2978807/asus-radeon-dual-rx-7600-o8g-v2-seconde-vie-parfai",
    "inStock": false,
    "lastSeen": "2026-07-06T12:02:39Z",
    "product": "Asus Radeon DUAL RX 7600 O8G V2-Seconde Vie-Parfait Etat"
   },
   {
    "shop": "bpm-power.com",
    "price": 285.0,
    "currency": "EUR",
    "url": "https://www.gputracker.eu/si-click/1/4318042/scheda-video-amd-powercolor-radeon-rx-7600-fighter",
    "inStock": true,
    "lastSeen": "2026-07-06T12:02:39Z",
    "product": "Scheda Video Amd PowerColor Radeon RX 7600 Fighter V2 8GB GDDR6 128bit Nero [RX 7600 8G-F/V2]"
   },
   {
    "shop": "amazon.fr",
    "price": 289.0,
    "currency": "EUR",
    "url": "https://www.gputracker.eu/si-click/1/3589689/xfx-vga-8gb-radeon-rx7600-speedster-swft210-core-g",
    "inStock": true,
    "lastSeen": "2026-07-06T12:02:39Z",
    "product": "XFX VGA 8GB Radeon RX7600 Speedster SWFT210 Core Gaming 3xDP/H"
   },
   {
    "shop": "jacob.de",
    "price": 291.0,
    "currency": "EUR",
    "url": "https://www.gputracker.eu/si-click/1/2435369/gigabyte-radeon-rx-7600-gaming-oc-gv-r76gaming-oc-",
    "inStock": true,
    "lastSeen": "2026-07-06T12:02:39Z",
    "product": "Gigabyte Radeon RX 7600 Gaming OC (GV-R76GAMING OC-8GD)"
   },
   {
    "shop": "amazon.fr",
    "price": 294.0,
    "currency": "EUR",
    "url": "https://www.gputracker.eu/si-click/1/3581999/asus-dual-radeontm-rx-7600-evo-oc-edition-8-go-gdd",
    "inStock": true,
    "lastSeen": "2026-07-06T12:02:39Z",
    "product": "ASUS Dual Radeon™ RX 7600 Evo OC Edition 8 Go GDDR6 - Carte Graphique (PCIe® 4.0, HDMI® 2.1, DisplayPort™ 1.4a, Conception à 2,5 Slots, Ventilateur..."
   },
   {
    "shop": "bpm-power.com",
    "price": 295.0,
    "currency": "EUR",
    "url": "https://www.gputracker.eu/si-click/1/2526143/scheda-video-amd-gigabyte-radeon-rx-7600-gaming-8g",
    "inStock": true,
    "lastSeen": "2026-07-06T12:02:39Z",
    "product": "Scheda Video Amd Gigabyte Radeon RX 7600 Gaming 8GB OC [GV-R76GAMING OC-8GD 1.0]"
   },
   {
    "shop": "compumsa.eu",
    "price": 299.0,
    "currency": "EUR",
    "url": "https://www.gputracker.eu/si-click/1/2427795/gigabyte-radeon-rx-7600-8gb-gaming-oc-carte-graphi",
    "inStock": false,
    "lastSeen": "2026-07-06T12:02:39Z",
    "product": "Gigabyte Radeon RX 7600 8GB Gaming OC - Carte graphique AMD"
   },
   {
    "shop": "topbiz.fr",
    "price": 301.0,
    "currency": "EUR",
    "url": "https://www.gputracker.eu/si-click/1/3610024/gigabyte-gaming-radeon-rx-7600-oc-8g-amd-8-go-gddr",
    "inStock": true,
    "lastSeen": "2026-07-06T12:02:39Z",
    "product": "Gigabyte GAMING Radeon RX 7600 OC 8G AMD 8 Go GDDR6"
   },
   {
    "shop": "bpm-power.com",
    "price": 302.0,
    "currency": "EUR",
    "url": "https://www.gputracker.eu/si-click/1/2456115/scheda-video-amd-sapphire-pulse-radeon-rx-7600-8gb",
    "inStock": true,
    "lastSeen": "2026-07-06T12:02:39Z",
    "product": "Scheda video Amd Sapphire Pulse Radeon RX 7600 8GB Gaming GDDR6 (UEFI) [11324-01-20G]"
   },
   {
    "shop": "codima.be",
    "price": 303.0,
    "currency": "EUR",
    "url": "https://www.gputracker.eu/si-click/1/4265237/powercolor-fighter-amd-radeon-rx-7600-8gb-gddr6",
    "inStock": false,
    "lastSeen": "2026-07-06T12:02:39Z",
    "product": "Powercolor Fighter AMD Radeon RX 7600 8GB GDDR6"
   },
   {
    "shop": "reichelt.de",
    "price": 309.0,
    "currency": "EUR",
    "url": "https://www.gputracker.eu/si-click/1/3018920/sap-11324-01-20g-sapphire-pulse-radeon-rx-7600-8gb",
    "inStock": true,
    "lastSeen": "2026-07-06T12:02:39Z",
    "product": "SAP 11324-01-20G - Sapphire Pulse Radeon RX 7600 8GB"
   },
   {
    "shop": "bpm-power.com",
    "price": 311.0,
    "currency": "EUR",
    "url": "https://www.gputracker.eu/si-click/1/3601479/scheda-video-amd-asus-dual-radeon-rx-7600-evo-8gb-",
    "inStock": false,
    "lastSeen": "2026-07-06T12:02:39Z",
    "product": "Scheda Video Amd Asus Dual Radeon RX 7600 Evo 8GB GDDR6 128bit Nero [90YV0LD0-M0NA00]"
   },
   {
    "shop": "compumsa.eu",
    "price": 314.0,
    "currency": "EUR",
    "url": "https://www.gputracker.eu/si-click/1/3601810/asus-radeon-rx-7600-8gb-dual-evo-oc-dual-rx7600-o8",
    "inStock": false,
    "lastSeen": "2026-07-06T12:02:39Z",
    "product": "Asus Radeon RX 7600 8GB Dual Evo OC - DUAL-RX7600-O8G-EVO - Carte graphique AMD"
   },
   {
    "shop": "jacob.de",
    "price": 314.0,
    "currency": "EUR",
    "url": "https://www.gputracker.eu/si-click/1/3444891/asus-dual-radeon-rx-7600-evo-8gb-90yv0ld0-m0na00",
    "inStock": true,
    "lastSeen": "2026-07-06T12:02:39Z",
    "product": "ASUS Dual Radeon RX 7600 EVO 8GB (90YV0LD0-M0NA00)"
   },
   {
    "shop": "bpm-power.com",
    "price": 316.0,
    "currency": "EUR",
    "url": "https://www.gputracker.eu/si-click/1/2474099/scheda-video-amd-asrock-radeon-rx7600-challenger-1",
    "inStock": true,
    "lastSeen": "2026-07-06T12:02:39Z",
    "product": "Scheda video Amd ASRock Radeon RX7600 Challenger 128 bits Nero [KGASRA706377002]"
   }
  ],
  "image": "images/amd-rx-7600.png",
  "sourceUrl": "https://www.gputracker.eu/en/search/category/1/graphics-cards/facet/2/graphics-chip/amd-rx-7600",
  "lastUpdated": "2026-07-06T12:02:39Z",
  "imageSource": "https://img-cdn-aws.gputracker.eu/fit-in/150x150/products/084/0191/0840191500725.png?signature=e852ecf39dbeed76022f028c7dfca1d8d802cd43f21dac41578cc9378499869a"
 },
 {
  "id": "amd-rx-7900-xtx",
  "brand": "AMD",
  "name": "AMD RX 7900 XTX",
  "index": 116.9,
  "vramGb": 24,
  "price": 1699.0,
  "tdp": 355,
  "priceMin": 1699.0,
  "prices": [
   {
    "shop": "amazon.fr",
    "price": 1699.0,
    "currency": "EUR",
    "url": "https://www.gputracker.eu/si-click/1/4629426/sapphire-nitro-amd-radeontm-rx-7900-xtx-gaming-oc-",
    "inStock": false,
    "lastSeen": "2026-07-06T12:02:39Z",
    "product": "Sapphire Nitro+ AMD Radeon™ RX 7900 XTX Gaming OC Vapor-X 24GB GDDR6 Dual HDMI/Dual DP Full"
   },
   {
    "shop": "amazon.fr",
    "price": 2283.0,
    "currency": "EUR",
    "url": "https://www.gputracker.eu/si-click/1/3407591/asus-tuf-gaming-radeon-rx-7900-xtx-oc-edition-cart",
    "inStock": true,
    "lastSeen": "2026-07-06T12:02:39Z",
    "product": "ASUS TUF GAMING Radeon RX 7900 XTX OC Edition – Carte graphique gaming (24GB GDDR6X, PCIe 4.0, HDMI 2.1a, DisplayPort 2.1, ventilateurs axiaux)"
   }
  ],
  "image": "images/amd-rx-7900-xtx.png",
  "sourceUrl": "https://www.gputracker.eu/en/search/category/1/graphics-cards/facet/2/graphics-chip/amd-rx-7900-xtx",
  "lastUpdated": "2026-07-06T12:02:39Z"
 },
 {
  "id": "amd-rx-9060-xt",
  "brand": "AMD",
  "name": "AMD RX 9060 XT",
  "index": 73.5,
  "vramGb": 8,
  "price": 329.0,
  "tdp": 150,
  "priceMin": 329.0,
  "prices": [
   {
    "shop": "bpm-power.com",
    "price": 329.0,
    "currency": "EUR",
    "url": "https://www.gputracker.eu/si-click/1/4182557/scheda-video-amd-sapphire-pulse-radeon-rx-9060-xt-",
    "inStock": true,
    "lastSeen": "2026-07-06T12:02:39Z",
    "product": "Scheda video Amd Sapphire Pulse Radeon RX 9060 XT Gaming Dual UEFI 8GB GDDR6 128bit Nero [11350-05-20G]"
   },
   {
    "shop": "rueducommerce.fr",
    "price": 330.0,
    "currency": "EUR",
    "url": "https://www.gputracker.eu/si-click/1/3900779/asrock-amd-radeon-rx-9060-xt-challenger-8gb-oc",
    "inStock": true,
    "lastSeen": "2026-07-06T12:02:39Z",
    "product": "ASRock AMD Radeon RX 9060 XT Challenger 8GB OC"
   },
   {
    "shop": "materiel.net",
    "price": 340.0,
    "currency": "EUR",
    "url": "https://www.gputracker.eu/si-click/1/3900646/asrock-amd-radeon-rx-9060-xt-challenger-8gb-oc",
    "inStock": true,
    "lastSeen": "2026-07-06T12:02:39Z",
    "product": "ASRock AMD Radeon RX 9060 XT Challenger 8GB OC"
   },
   {
    "shop": "ldlc.com",
    "price": 340.0,
    "currency": "EUR",
    "url": "https://www.gputracker.eu/si-click/1/3900739/asrock-amd-radeon-rx-9060-xt-challenger-8gb-oc",
    "inStock": true,
    "lastSeen": "2026-07-06T12:02:39Z",
    "product": "ASRock AMD Radeon RX 9060 XT Challenger 8GB OC"
   },
   {
    "shop": "grosbill.com",
    "price": 340.0,
    "currency": "EUR",
    "url": "https://www.gputracker.eu/si-click/1/4259038/gigabyte-radeon-rx-9060-xt-gaming-oc-8g",
    "inStock": false,
    "lastSeen": "2026-07-06T12:02:39Z",
    "product": "Gigabyte Radeon RX 9060 XT GAMING OC 8G"
   },
   {
    "shop": "compumsa.eu",
    "price": 344.0,
    "currency": "EUR",
    "url": "https://www.gputracker.eu/si-click/1/3913347/asrock-radeon-rx-9060-xt-8gb-challenger-oc-rx9060x",
    "inStock": false,
    "lastSeen": "2026-07-06T12:02:39Z",
    "product": "ASRock Radeon RX 9060 XT 8GB Challenger OC - RX9060XT CL 8GO - Carte graphique AMD"
   },
   {
    "shop": "cybertek.fr",
    "price": 345.0,
    "currency": "EUR",
    "url": "https://www.gputracker.eu/si-click/1/4021007/gigabyte-radeon-rx-9060-xt-gaming-oc-8g",
    "inStock": false,
    "lastSeen": "2026-07-06T12:02:39Z",
    "product": "Gigabyte Radeon RX 9060 XT GAMING OC 8G"
   },
   {
    "shop": "amazon.de",
    "price": 345.0,
    "currency": "EUR",
    "url": "https://www.gputracker.eu/si-click/1/3901048/gigabyte-radeon-rx-9060-xt-gaming-oc-8g-graphics-c",
    "inStock": true,
    "lastSeen": "2026-07-06T12:02:39Z",
    "product": "Gigabyte Radeon RX 9060 XT Gaming OC 8G Graphics Card - 8GB GDDR6, 128bit, PCI-E 5.0, 3320 MHz Core Clock, 2 x DisplayPort, 1 x HDMI, GV-R9060XTGAM..."
   },
   {
    "shop": "compumsa.eu",
    "price": 346.0,
    "currency": "EUR",
    "url": "https://www.gputracker.eu/si-click/1/4154602/sapphire-radeon-rx-9060xt-8gb-pulse-gaming-carte-g",
    "inStock": false,
    "lastSeen": "2026-07-06T12:02:39Z",
    "product": "Sapphire Radeon RX 9060XT 8GB Pulse Gaming - Carte graphique AMD"
   },
   {
    "shop": "compumsa.eu",
    "price": 349.0,
    "currency": "EUR",
    "url": "https://www.gputracker.eu/si-click/1/3913348/powercolor-radeon-rx-9060-xt-8gb-reaper-carte-grap",
    "inStock": false,
    "lastSeen": "2026-07-06T12:02:39Z",
    "product": "PowerColor Radeon RX 9060 XT 8GB Reaper - Carte graphique AMD"
   },
   {
    "shop": "amazon.fr",
    "price": 349.0,
    "currency": "EUR",
    "url": "https://www.gputracker.eu/si-click/1/3904500/gigabyte-radeon-rx-9060-xt-gaming-oc-8g-carte-grap",
    "inStock": true,
    "lastSeen": "2026-07-06T12:02:39Z",
    "product": "GIGABYTE Radeon RX 9060 XT Gaming OC 8G Carte Graphique - 8GB GDDR6, 128bit, PCI-E 5.0, 3320 MHz Fréquence du cœur, 2 x DisplayPort, 1 x HDMI, GV-R..."
   },
   {
    "shop": "materiel.net",
    "price": 350.0,
    "currency": "EUR",
    "url": "https://www.gputracker.eu/si-click/1/3900649/gigabyte-radeon-rx-9060-xt-gaming-oc-8g",
    "inStock": true,
    "lastSeen": "2026-07-06T12:02:39Z",
    "product": "Gigabyte Radeon RX 9060 XT GAMING OC 8G"
   },
   {
    "shop": "codima.be",
    "price": 350.0,
    "currency": "EUR",
    "url": "https://www.gputracker.eu/si-click/1/4265254/powercolor-reaper-radeon-rx-9060-xt-8gb",
    "inStock": true,
    "lastSeen": "2026-07-06T12:02:39Z",
    "product": "Powercolor Reaper Radeon RX 9060 XT 8GB"
   },
   {
    "shop": "bpm-power.com",
    "price": 352.0,
    "currency": "EUR",
    "url": "https://www.gputracker.eu/si-click/1/4077704/scheda-video-amd-gigabyte-radeon-rx-9060-xt-gaming",
    "inStock": true,
    "lastSeen": "2026-07-06T12:02:39Z",
    "product": "Scheda video Amd Gigabyte Radeon RX 9060 XT Gaming OC 8GB GDDR6 128bit Nero [GV-R9060XTGAMING OC-8GD]"
   },
   {
    "shop": "alternate.fr",
    "price": 353.0,
    "currency": "EUR",
    "url": "https://www.gputracker.eu/si-click/1/4360734/asrock-radeon-rx-9060-xt-steel-legend-oc-8gb-carte",
    "inStock": false,
    "lastSeen": "2026-07-06T12:02:39Z",
    "product": "ASRock Radeon RX 9060 XT STEEL LEGEND OC 8GB, Carte graphique"
   },
   {
    "shop": "jacob.de",
    "price": 357.0,
    "currency": "EUR",
    "url": "https://www.gputracker.eu/si-click/1/4161693/sapphire-radeon-rx9060xt-pulse-gaming-gddr6-2xhdmi",
    "inStock": true,
    "lastSeen": "2026-07-06T12:02:39Z",
    "product": "Sapphire Radeon RX9060XT Pulse Gaming GDDR6 2xHDMI DP - 8.192 MB (11350-05-20G)"
   },
   {
    "shop": "rueducommerce.fr",
    "price": 360.0,
    "currency": "EUR",
    "url": "https://www.gputracker.eu/si-click/1/3900782/gigabyte-radeon-rx-9060-xt-gaming-oc-8g",
    "inStock": true,
    "lastSeen": "2026-07-06T12:02:39Z",
    "product": "Gigabyte Radeon RX 9060 XT GAMING OC 8G"
   },
   {
    "shop": "bpm-power.com",
    "price": 368.0,
    "currency": "EUR",
    "url": "https://www.gputracker.eu/si-click/1/4077736/scheda-video-amd-sapphire-radeon-rx-9060-xt-pulse-",
    "inStock": true,
    "lastSeen": "2026-07-06T12:02:39Z",
    "product": "Scheda Video Amd Sapphire Radeon RX 9060 XT Pulse Gaming 8GB GDDR6 128bit Nero [11350-04-20G]"
   },
   {
    "shop": "jacob.de",
    "price": 369.0,
    "currency": "EUR",
    "url": "https://www.gputracker.eu/si-click/1/3908530/sapphire-radeon-rx9060xt-pulse-gaming-oc-8gbgddr6-",
    "inStock": true,
    "lastSeen": "2026-07-06T12:02:39Z",
    "product": "Sapphire Radeon RX9060XT Pulse Gaming OC 8GBGDDR6 2xHDMI DP (11350-04-20G)"
   },
   {
    "shop": "reichelt.de",
    "price": 369.0,
    "currency": "EUR",
    "url": "https://www.gputracker.eu/si-click/1/3913329/pcg-75988-powercolor-rx-9060-xt-reaper-8-gb",
    "inStock": true,
    "lastSeen": "2026-07-06T12:02:39Z",
    "product": "PCG 75988 - PowerColor RX 9060 XT Reaper 8 GB"
   }
  ],
  "image": "images/amd-rx-9060-xt.png",
  "sourceUrl": "https://www.gputracker.eu/en/search/category/1/graphics-cards/facet/2/graphics-chip/amd-rx-9060-xt",
  "lastUpdated": "2026-07-06T12:02:39Z",
  "imageSource": "https://img-cdn-aws.gputracker.eu/fit-in/150x150/products/489/5106/4895106297333.png?signature=ef6baac942547e9ddc9fe1a97bf56b68b75531f32c95b9397ddbf6089937c832"
 },
 {
  "id": "amd-rx-9070",
  "brand": "AMD",
  "name": "AMD RX 9070",
  "index": 94.5,
  "vramGb": 12,
  "price": 550.0,
  "tdp": 220,
  "priceMin": 550.0,
  "prices": [
   {
    "shop": "grosbill.com",
    "price": 550.0,
    "currency": "EUR",
    "url": "https://www.gputracker.eu/si-click/1/4307915/asus-prime-radeon-rx-9070-evo-oc-edition-16gb-gddr",
    "inStock": true,
    "lastSeen": "2026-07-06T12:02:39Z",
    "product": "Asus Prime Radeon RX 9070 EVO OC Edition 16GB GDDR6"
   },
   {
    "shop": "cybertek.fr",
    "price": 550.0,
    "currency": "EUR",
    "url": "https://www.gputracker.eu/si-click/1/3702543/asus-prime-radeon-rx-9070-oc-edition-16gb-gddr6",
    "inStock": true,
    "lastSeen": "2026-07-06T12:02:39Z",
    "product": "Asus Prime Radeon RX 9070 OC Edition 16GB GDDR6"
   },
   {
    "shop": "bpm-power.com",
    "price": 556.0,
    "currency": "EUR",
    "url": "https://www.gputracker.eu/si-click/1/4671636/scheda-video-sapphire-pulse-amd-radeon-rx-9070-gre",
    "inStock": true,
    "lastSeen": "2026-07-06T12:02:39Z",
    "product": "Scheda Video Sapphire Pulse AMD Radeon RX 9070 Gre Gaming OC 12GB GDDR6 192bit Nero [11354-01-20G]"
   },
   {
    "shop": "amazon.de",
    "price": 558.0,
    "currency": "EUR",
    "url": "https://www.gputracker.eu/si-click/1/4700491/asus-prime-radeon-rx-9070-gre-oc-edition-gaming-gr",
    "inStock": true,
    "lastSeen": "2026-07-06T12:02:39Z",
    "product": "ASUS Prime Radeon RX 9070 GRE OC Edition Gaming Graphics Card (AMD Radeon RX 9070, PCIe 5.0, HDMI/DP 2.1, Dual BIOS Switch, Axial Tech Fan, 2.5 Slo..."
   },
   {
    "shop": "alternate.fr",
    "price": 564.0,
    "currency": "EUR",
    "url": "https://www.gputracker.eu/si-click/1/4664619/sapphire-pulse-rx-9070-gre-oc-carte-graphique",
    "inStock": true,
    "lastSeen": "2026-07-06T12:02:39Z",
    "product": "SAPPHIRE PULSE RX 9070 GRE OC, Carte graphique"
   },
   {
    "shop": "grosbill.com",
    "price": 569.0,
    "currency": "EUR",
    "url": "https://www.gputracker.eu/si-click/1/4664591/sapphire-pulse-amd-rx-9070-gre-oc-12go",
    "inStock": true,
    "lastSeen": "2026-07-06T12:02:39Z",
    "product": "Sapphire Pulse AMD RX 9070 GRE OC 12Go"
   },
   {
    "shop": "cybertek.fr",
    "price": 569.0,
    "currency": "EUR",
    "url": "https://www.gputracker.eu/si-click/1/4664585/sapphire-pulse-amd-rx-9070-gre-oc-12go",
    "inStock": true,
    "lastSeen": "2026-07-06T12:02:39Z",
    "product": "Sapphire Pulse AMD RX 9070 GRE OC 12Go"
   },
   {
    "shop": "ldlc.com",
    "price": 570.0,
    "currency": "EUR",
    "url": "https://www.gputracker.eu/si-click/1/4664506/sapphire-pulse-amd-radeon-rx-9070-gre-gaming-oc-12",
    "inStock": true,
    "lastSeen": "2026-07-06T12:02:39Z",
    "product": "Sapphire PULSE AMD Radeon RX 9070 GRE Gaming OC 12GB"
   },
   {
    "shop": "materiel.net",
    "price": 570.0,
    "currency": "EUR",
    "url": "https://www.gputracker.eu/si-click/1/4663518/sapphire-pulse-amd-radeon-rx-9070-gre",
    "inStock": true,
    "lastSeen": "2026-07-06T12:02:39Z",
    "product": "Sapphire PULSE AMD Radeon RX 9070 GRE"
   },
   {
    "shop": "rueducommerce.fr",
    "price": 570.0,
    "currency": "EUR",
    "url": "https://www.gputracker.eu/si-click/1/4670176/sapphire-pulse-amd-radeon-rx-9070-gre-gaming-oc-12",
    "inStock": true,
    "lastSeen": "2026-07-06T12:02:39Z",
    "product": "Sapphire PULSE AMD Radeon RX 9070 GRE Gaming OC 12GB"
   },
   {
    "shop": "grosbill.com",
    "price": 590.0,
    "currency": "EUR",
    "url": "https://www.gputracker.eu/si-click/1/4688146/asus-prime-radeon-rx-9070-gre-oc-edition-12gb-gddr",
    "inStock": true,
    "lastSeen": "2026-07-06T12:02:39Z",
    "product": "Asus Prime Radeon RX 9070 GRE OC Edition 12GB GDDR6"
   },
   {
    "shop": "jacob.de",
    "price": 591.0,
    "currency": "EUR",
    "url": "https://www.gputracker.eu/si-click/1/4668877/sapphire-vga-12gb-rx9070gre-pulse-gaming-oc-2xhdmi",
    "inStock": true,
    "lastSeen": "2026-07-06T12:02:39Z",
    "product": "Sapphire VGA 12GB RX9070GRE PULSE GAMING OC 2xHDMI/2xDP PULSE AMD RADEON RX 9070 GRE GAMING OC 12GB DUAL H (11354-01-20G)"
   },
   {
    "shop": "jacob.de",
    "price": 597.0,
    "currency": "EUR",
    "url": "https://www.gputracker.eu/si-click/1/4700441/vga-gigabyte-radeon-rx-9070-gre-gaming-12gb-oc-gv-",
    "inStock": true,
    "lastSeen": "2026-07-06T12:02:39Z",
    "product": "VGA Gigabyte Radeon RX 9070 GRE GAMING 12GB OC (GV-R907GREGAMING OC-12GD)"
   },
   {
    "shop": "amazon.fr",
    "price": 599.0,
    "currency": "EUR",
    "url": "https://www.gputracker.eu/si-click/1/4727472/gigabyte-radeon-rx-9070-gre-gaming-oc-12g-carte-gr",
    "inStock": true,
    "lastSeen": "2026-07-06T12:02:39Z",
    "product": "GIGABYTE Radeon RX 9070 GRE Gaming OC 12G – Carte Graphique, 12GB GDDR6, 192bit, PCI-E 5.0, 2920 MHz Core Clock, 2 × DisplayPort, 2 × HDMI, GV-R907..."
   },
   {
    "shop": "amazon.de",
    "price": 599.0,
    "currency": "EUR",
    "url": "https://www.gputracker.eu/si-click/1/4495688/gigabyte-radeon-rx-9070-gaming-16gb-graphics-card-",
    "inStock": true,
    "lastSeen": "2026-07-06T12:02:39Z",
    "product": "Gigabyte Radeon RX 9070 Gaming 16GB Graphics Card - 16GB GDDR6, 256bit, PCI-E 5.0, 2520 MHz Core Clock, 2 x DisplayPort, 2 x HDMI, GV-R9070GAMING-16GD"
   },
   {
    "shop": "grosbill.com",
    "price": 600.0,
    "currency": "EUR",
    "url": "https://www.gputracker.eu/si-click/1/4681845/gigabyte-radeon-rx-9070-gre-gaming-oc-12g",
    "inStock": true,
    "lastSeen": "2026-07-06T12:02:39Z",
    "product": "Gigabyte Radeon RX 9070 GRE GAMING OC 12G"
   }
  ],
  "image": "images/amd-rx-9070.png",
  "sourceUrl": "https://www.gputracker.eu/en/search/category/1/graphics-cards/facet/2/graphics-chip/amd-rx-9070",
  "lastUpdated": "2026-07-06T12:02:39Z",
  "imageSource": "https://img-cdn-aws.gputracker.eu/fit-in/150x150/products/471/1636/4711636204101.png?signature=ca312f03256e579f86d0450ca27eefff828fc2c4c4aa195012652d0dcb2a56b7"
 },
 {
  "id": "amd-rx-9070-xt",
  "brand": "AMD",
  "name": "AMD RX 9070 XT",
  "index": 100.1,
  "vramGb": 16,
  "price": 650.0,
  "tdp": 304,
  "priceMin": 650.0,
  "prices": [
   {
    "shop": "materiel.net",
    "price": 650.0,
    "currency": "EUR",
    "url": "https://www.gputracker.eu/si-click/1/4324606/gigabyte-radeon-rx-9070-xt-gaming-16g",
    "inStock": true,
    "lastSeen": "2026-07-06T12:02:39Z",
    "product": "Gigabyte Radeon RX 9070 XT GAMING 16G"
   },
   {
    "shop": "grosbill.com",
    "price": 650.0,
    "currency": "EUR",
    "url": "https://www.gputracker.eu/si-click/1/3702642/asus-prime-radeon-rx-9070-xt-oc-edition-16gb-gddr6",
    "inStock": false,
    "lastSeen": "2026-07-06T12:02:39Z",
    "product": "Asus Prime Radeon RX 9070 XT OC Edition 16GB GDDR6"
   },
   {
    "shop": "cybertek.fr",
    "price": 660.0,
    "currency": "EUR",
    "url": "https://www.gputracker.eu/si-click/1/3702547/asus-prime-radeon-rx-9070-xt-oc-edition-16gb-gddr6",
    "inStock": true,
    "lastSeen": "2026-07-06T12:02:39Z",
    "product": "Asus Prime Radeon RX 9070 XT OC Edition 16GB GDDR6"
   },
   {
    "shop": "amazon.de",
    "price": 660.0,
    "currency": "EUR",
    "url": "https://www.gputracker.eu/si-click/1/4326622/gigabyte-radeon-rx-9070-xt-gaming-oc-ice-16g-graph",
    "inStock": true,
    "lastSeen": "2026-07-06T12:02:39Z",
    "product": "Gigabyte Radeon RX 9070 XT Gaming OC Ice 16G Graphics Card - 16GB GDDR6, 256bit, PCI-E 5.0, 3060 MHz Core Clock, 2 x DisplayPort, 2 x HDMI, GV-R907..."
   },
   {
    "shop": "amazon.de",
    "price": 662.0,
    "currency": "EUR",
    "url": "https://www.gputracker.eu/si-click/1/3702444/asus-prime-radeon-rx-9070-xt-oc-edition-16gb-gddr6",
    "inStock": true,
    "lastSeen": "2026-07-06T12:02:39Z",
    "product": "ASUS Prime Radeon RX 9070 XT OC Edition 16GB GDDR6 Gaming Graphics Card (AMD Radeon RX9070XT, PCIe 5.0, 1x HDMI 2.1b, 3X DisplayPort 2.1a, 2.5 Slot..."
   },
   {
    "shop": "amazon.de",
    "price": 666.0,
    "currency": "EUR",
    "url": "https://www.gputracker.eu/si-click/1/3758768/gigabyte-radeon-rx-9070-xt-gaming-oc-16g-graphics-",
    "inStock": true,
    "lastSeen": "2026-07-06T12:02:39Z",
    "product": "Gigabyte Radeon RX 9070 XT Gaming OC 16G Graphics Card - 16 GB GDDR6, 256 Bit, PCI-E 5.0, 3060 MHz Core Frequency, 2 x DisplayPort, 2 x HDMI, GV-R9..."
   },
   {
    "shop": "amazon.de",
    "price": 669.0,
    "currency": "EUR",
    "url": "https://www.gputracker.eu/si-click/1/4189273/gigabyte-radeon-rx-9070-xt-gaming-16g-graphics-car",
    "inStock": true,
    "lastSeen": "2026-07-06T12:02:39Z",
    "product": "Gigabyte Radeon RX 9070 XT Gaming 16G Graphics Card - 16GB GDDR6, 256-Bit, PCI-E 5.0, 2970MHz Core Frequency, 2 x DisplayPort 2.1a, 2 x HDMI 2.1b, ..."
   },
   {
    "shop": "materiel.net",
    "price": 670.0,
    "currency": "EUR",
    "url": "https://www.gputracker.eu/si-click/1/3702573/gigabyte-radeon-rx-9070-xt-gaming-oc-16g",
    "inStock": true,
    "lastSeen": "2026-07-06T12:02:39Z",
    "product": "Gigabyte Radeon RX 9070 XT GAMING OC 16G"
   },
   {
    "shop": "rueducommerce.fr",
    "price": 680.0,
    "currency": "EUR",
    "url": "https://www.gputracker.eu/si-click/1/3754771/gigabyte-radeon-rx-9070-xt-gaming-oc-16g",
    "inStock": true,
    "lastSeen": "2026-07-06T12:02:39Z",
    "product": "Gigabyte Radeon RX 9070 XT GAMING OC 16G"
   },
   {
    "shop": "amazon.de",
    "price": 687.0,
    "currency": "EUR",
    "url": "https://www.gputracker.eu/si-click/1/4725021/gigabyte-radeon-rx-9070-xt-gaming-oc-16g-graphics-",
    "inStock": true,
    "lastSeen": "2026-07-06T12:02:39Z",
    "product": "GIGABYTE Radeon RX 9070 XT Gaming OC 16G Graphics Card, PCIe 5.0, 16GB GDDR6, GV-R9070XTGAMING OC-16GD Graphics Card"
   },
   {
    "shop": "amazon.fr",
    "price": 689.0,
    "currency": "EUR",
    "url": "https://www.gputracker.eu/si-click/1/4313972/gigabyte-radeon-rx-9070-xt-gaming-oc-ice-16g-carte",
    "inStock": true,
    "lastSeen": "2026-07-06T12:02:39Z",
    "product": "GIGABYTE Radeon RX 9070 XT Gaming OC Ice 16G Carte Graphique - 16GB GDDR6, 256bit, PCI-E 5.0, 3060 MHz Fréquence du cœur, 2 x DisplayPort, 2 x HDMI..."
   },
   {
    "shop": "ldlc.com",
    "price": 690.0,
    "currency": "EUR",
    "url": "https://www.gputracker.eu/si-click/1/4316129/gigabyte-radeon-rx-9070-xt-gaming-16g",
    "inStock": true,
    "lastSeen": "2026-07-06T12:02:39Z",
    "product": "Gigabyte Radeon RX 9070 XT GAMING 16G"
   },
   {
    "shop": "materiel.net",
    "price": 690.0,
    "currency": "EUR",
    "url": "https://www.gputracker.eu/si-click/1/4278277/gigabyte-radeon-rx-9070-xt-gaming-oc-ice-16g",
    "inStock": true,
    "lastSeen": "2026-07-06T12:02:39Z",
    "product": "Gigabyte Radeon RX 9070 XT GAMING OC ICE 16G"
   },
   {
    "shop": "amazon.fr",
    "price": 699.0,
    "currency": "EUR",
    "url": "https://www.gputracker.eu/si-click/1/4362079/scheda-grafica-asrock-90-ga61zz-00uanf-radeon-rx-9",
    "inStock": true,
    "lastSeen": "2026-07-06T12:02:39Z",
    "product": "Scheda Grafica ASRock 90-GA61ZZ-00UANF Radeon RX 9070 XT 16 GB GDDR6"
   },
   {
    "shop": "codima.be",
    "price": 699.0,
    "currency": "EUR",
    "url": "https://www.gputracker.eu/si-click/1/4396431/xfx-swift-amd-radeon-rx-9070xt-triple-fan-gaming-e",
    "inStock": true,
    "lastSeen": "2026-07-06T12:02:39Z",
    "product": "XFX Swift AMD Radeon RX 9070XT Triple Fan Gaming Edition"
   },
   {
    "shop": "ldlc.com",
    "price": 700.0,
    "currency": "EUR",
    "url": "https://www.gputracker.eu/si-click/1/3702598/gigabyte-radeon-rx-9070-xt-gaming-oc-16g",
    "inStock": true,
    "lastSeen": "2026-07-06T12:02:39Z",
    "product": "Gigabyte Radeon RX 9070 XT GAMING OC 16G"
   },
   {
    "shop": "rueducommerce.fr",
    "price": 700.0,
    "currency": "EUR",
    "url": "https://www.gputracker.eu/si-click/1/4294627/asrock-amd-radeon-rx-9070-xt-challenger-16gb",
    "inStock": true,
    "lastSeen": "2026-07-06T12:02:39Z",
    "product": "ASRock AMD Radeon RX 9070 XT Challenger 16GB"
   },
   {
    "shop": "bpm-power.com",
    "price": 706.0,
    "currency": "EUR",
    "url": "https://www.gputracker.eu/si-click/1/3704722/scheda-video-amd-gigabyte-radeon-rx-9070-xt-gaming",
    "inStock": false,
    "lastSeen": "2026-07-06T12:02:39Z",
    "product": "Scheda Video Amd Gigabyte Radeon RX 9070 XT GAMING OC 16GB [GV-R9070XTGAMING OC-16GD]"
   },
   {
    "shop": "alternate.fr",
    "price": 706.0,
    "currency": "EUR",
    "url": "https://www.gputracker.eu/si-click/1/3810327/xfx-radeon-rx-9070-xt-swift-carte-graphique",
    "inStock": false,
    "lastSeen": "2026-07-06T12:02:39Z",
    "product": "XFX Radeon RX 9070 XT Swift, Carte graphique"
   }
  ],
  "image": "images/amd-rx-9070-xt.png",
  "sourceUrl": "https://www.gputracker.eu/en/search/category/1/graphics-cards/facet/2/graphics-chip/amd-rx-9070-xt",
  "lastUpdated": "2026-07-06T12:02:39Z",
  "imageSource": "https://img-cdn-aws.gputracker.eu/fit-in/150x150/products/471/9331/4719331356149.png?signature=1203855a7e1132ec61e25448fbfc21c997ca94c1430c7bed50931a91d9cfcf66"
 },
 {
  "id": "intel-arc-a310",
  "brand": "Intel",
  "name": "INTEL ARC A310",
  "index": 20.3,
  "vramGb": 4,
  "price": 132.0,
  "tdp": null,
  "priceMin": 132.0,
  "prices": [
   {
    "shop": "jacob.de",
    "price": 132.0,
    "currency": "EUR",
    "url": "https://www.gputracker.eu/si-click/1/4186716/asrock-intel-arc-a310-low-profile-4gb-90-g4nzz-00u",
    "inStock": true,
    "lastSeen": "2026-07-06T12:02:39Z",
    "product": "Asrock Intel Arc A310 Low Profile 4GB (90-G4NZZ-00UANF)"
   },
   {
    "shop": "topbiz.fr",
    "price": 137.0,
    "currency": "EUR",
    "url": "https://www.gputracker.eu/si-click/1/4383601/asrock-intel-arc-a310-low-profile-4gb-4-go-gddr6",
    "inStock": true,
    "lastSeen": "2026-07-06T12:02:39Z",
    "product": "Asrock Intel Arc A310 Low Profile 4GB 4 Go GDDR6"
   },
   {
    "shop": "bpm-power.com",
    "price": 139.0,
    "currency": "EUR",
    "url": "https://www.gputracker.eu/si-click/1/3601478/scheda-video-intel-sparkle-intel-arc-a310-4gb-omni",
    "inStock": true,
    "lastSeen": "2026-07-06T12:02:39Z",
    "product": "Scheda Video Intel Sparkle Intel Arc A310 4GB Omni View GDDR6 4x HDMI Nero [SA310F-4G]"
   },
   {
    "shop": "amazon.fr",
    "price": 140.0,
    "currency": "EUR",
    "url": "https://www.gputracker.eu/si-click/1/3598852/sparkle-intel-arc-a310-eco-4-go-gddr6-50-w-tbp-pro",
    "inStock": true,
    "lastSeen": "2026-07-06T12:02:39Z",
    "product": "Sparkle Intel Arc A310 ECO, 4 Go GDDR6, 50 W TBP, Profil Bas, Ventilateur Unique, Fente Unique, HDMI x1, Mini DisplayPort x2, SA310L-4G"
   },
   {
    "shop": "bpm-power.com",
    "price": 141.0,
    "currency": "EUR",
    "url": "https://www.gputracker.eu/si-click/1/3211415/scheda-video-sparkle-sa310c-4g-a310-eco-4gb-gddr6-",
    "inStock": true,
    "lastSeen": "2026-07-06T12:02:39Z",
    "product": "Scheda Video Sparkle SA310C-4G A310 Eco 4GB GDDR6 64bit Blu [1A1-S00401900G]"
   },
   {
    "shop": "jacob.de",
    "price": 144.0,
    "currency": "EUR",
    "url": "https://www.gputracker.eu/si-click/1/3577899/sparkle-intel-arc-a310-omni-view-4gb-gddr6-grafikk",
    "inStock": true,
    "lastSeen": "2026-07-06T12:02:39Z",
    "product": "Sparkle Intel Arc A310 OMNI View 4GB GDDR6 Grafikkarte PCIe 4.0 x8 (SA310F-4G)"
   },
   {
    "shop": "jacob.de",
    "price": 149.0,
    "currency": "EUR",
    "url": "https://www.gputracker.eu/si-click/1/3081023/sparkle-intel-arc-a310-4gb-eco-gddr6-vga-card-sa31",
    "inStock": true,
    "lastSeen": "2026-07-06T12:02:39Z",
    "product": "SPARKLE Intel ARC A310 4GB ECO GDDR6 VGA Card (SA310C-4G)"
   }
  ],
  "image": "images/intel-arc-a310.png",
  "sourceUrl": "https://www.gputracker.eu/en/search/category/1/graphics-cards/facet/2/graphics-chip/intel-arc-a310",
  "lastUpdated": "2026-07-06T12:02:39Z",
  "imageSource": "https://img-cdn-aws.gputracker.eu/fit-in/150x150/products/471/0483/4710483943867.png?signature=b2ebcc924c15f5bfba0929b344493858f67b1c77daa8ff558f5ca5b9b6152f8a"
 },
 {
  "id": "intel-arc-a380",
  "brand": "Intel",
  "name": "INTEL ARC A380",
  "index": 23.5,
  "vramGb": 6,
  "price": 157.0,
  "tdp": 75,
  "priceMin": 157.0,
  "prices": [
   {
    "shop": "alternate.fr",
    "price": 157.0,
    "currency": "EUR",
    "url": "https://www.gputracker.eu/si-click/1/2289358/asrock-intel-arc-a380-challenger-itx-6go-oc-carte-",
    "inStock": false,
    "lastSeen": "2026-07-06T12:02:39Z",
    "product": "ASRock Intel Arc A380 Challenger ITX 6Go OC, Carte graphique"
   },
   {
    "shop": "reichelt.de",
    "price": 160.0,
    "currency": "EUR",
    "url": "https://www.gputracker.eu/si-click/1/2236698/asr-90ga3kzz-asrock-intel-arc-a380-challenger-itx-",
    "inStock": true,
    "lastSeen": "2026-07-06T12:02:39Z",
    "product": "ASR 90GA3KZZ - ASRock Intel Arc A380 Challenger ITX 6GB OC"
   },
   {
    "shop": "bpm-power.com",
    "price": 163.0,
    "currency": "EUR",
    "url": "https://www.gputracker.eu/si-click/1/2028556/scheda-video-asrock-intel-arc-a380-challenger-itx-",
    "inStock": true,
    "lastSeen": "2026-07-06T12:02:39Z",
    "product": "Scheda Video Asrock Intel Arc A380 Challenger ITX 6GB OC [A380 CLI 6GO]"
   },
   {
    "shop": "bpm-power.com",
    "price": 167.0,
    "currency": "EUR",
    "url": "https://www.gputracker.eu/si-click/1/3178732/scheda-video-intel-sparkle-intel-arc-a380-elf-6gb-",
    "inStock": true,
    "lastSeen": "2026-07-06T12:02:39Z",
    "product": "Scheda Video Intel Sparkle Intel Arc A380 ELF 6GB GDDR6 96bit Blu [SA380E-6G]"
   },
   {
    "shop": "jacob.de",
    "price": 170.0,
    "currency": "EUR",
    "url": "https://www.gputracker.eu/si-click/1/2084178/asrock-challenger-itx-arc-a380-6gb-oc-grafikkarte-",
    "inStock": true,
    "lastSeen": "2026-07-06T12:02:39Z",
    "product": "ASRock Challenger ITX Arc A380 6GB OC Grafikkarte - 6GB GDDR6, PCIe 4.0 x8, HDMI + 3x DP (90-GA3KZZ-00UANF)"
   },
   {
    "shop": "jacob.de",
    "price": 175.0,
    "currency": "EUR",
    "url": "https://www.gputracker.eu/si-click/1/2671983/sparkle-technology-intel-arc-a380-elf-sa380e-6g",
    "inStock": true,
    "lastSeen": "2026-07-06T12:02:39Z",
    "product": "Sparkle Technology Intel Arc A380 ELF (SA380E-6G)"
   },
   {
    "shop": "topbiz.fr",
    "price": 188.0,
    "currency": "EUR",
    "url": "https://www.gputracker.eu/si-click/1/3867635/asrock-challenger-intel-arc-a380-itx-6gb-oc-6-go-g",
    "inStock": true,
    "lastSeen": "2026-07-06T12:02:39Z",
    "product": "Asrock Challenger Intel Arc A380 ITX 6GB OC 6 Go GDDR6"
   }
  ],
  "image": "images/intel-arc-a380.png",
  "sourceUrl": "https://www.gputracker.eu/en/search/category/1/graphics-cards/facet/2/graphics-chip/intel-arc-a380",
  "lastUpdated": "2026-07-06T12:02:39Z",
  "imageSource": "https://img-cdn-aws.gputracker.eu/fit-in/150x150/products/471/0483/4710483939365.png?signature=602d6231c701794a88a02e2bc89cc40a96d75a6031223abd16c8bcf61429c99a"
 },
 {
  "id": "intel-arc-a750",
  "brand": "Intel",
  "name": "INTEL ARC A750",
  "index": 47.0,
  "vramGb": 8,
  "price": 211.0,
  "tdp": 225,
  "priceMin": 211.0,
  "prices": [
   {
    "shop": "bpm-power.com",
    "price": 211.0,
    "currency": "EUR",
    "url": "https://www.gputracker.eu/si-click/1/3309239/scheda-video-intel-sparkle-intel-arc-a750-titan-oc",
    "inStock": true,
    "lastSeen": "2026-07-06T12:02:39Z",
    "product": "Scheda Video Intel Sparkle Intel Arc A750 Titan OC 8GB GDDR6 256bit Blu [SA750T-8GOC]"
   },
   {
    "shop": "amazon.de",
    "price": 218.0,
    "currency": "EUR",
    "url": "https://www.gputracker.eu/si-click/1/3852622/asrock-intel-arc-a750-cl-se-8go-8gb-gddr6-2xhdmi-2",
    "inStock": true,
    "lastSeen": "2026-07-06T12:02:39Z",
    "product": "ASRock Intel Arc A750 CL SE 8GO 8GB GDDR6 2xHDMI/ 2xDP"
   },
   {
    "shop": "bpm-power.com",
    "price": 219.0,
    "currency": "EUR",
    "url": "https://www.gputracker.eu/si-click/1/3666850/scheda-video-asrock-intel-arc-a750-8gb-challenger-",
    "inStock": true,
    "lastSeen": "2026-07-06T12:02:39Z",
    "product": "Scheda Video ASRock Intel ARC A750 8GB Challenger SE OC [A750 CL SE 8GO]"
   },
   {
    "shop": "alternate.fr",
    "price": 220.0,
    "currency": "EUR",
    "url": "https://www.gputracker.eu/si-click/1/3967368/asrock-intel-arc-a750-challenger-se-8gb-oc-carte-g",
    "inStock": true,
    "lastSeen": "2026-07-06T12:02:39Z",
    "product": "ASRock Intel Arc A750 Challenger SE 8GB OC, Carte graphique"
   },
   {
    "shop": "reichelt.de",
    "price": 220.0,
    "currency": "EUR",
    "url": "https://www.gputracker.eu/si-click/1/3699065/asr-90ga5azz-asrock-intel-arc-a750-challenger-se-8",
    "inStock": true,
    "lastSeen": "2026-07-06T12:02:39Z",
    "product": "ASR 90GA5AZZ - ASRock Intel Arc A750 Challenger SE 8 GB OC"
   },
   {
    "shop": "jacob.de",
    "price": 223.0,
    "currency": "EUR",
    "url": "https://www.gputracker.eu/si-click/1/2666641/sparkle-intel-a750-titan-oc-triple-fan-8gb-vga-car",
    "inStock": true,
    "lastSeen": "2026-07-06T12:02:39Z",
    "product": "SPARKLE Intel A750 Titan OC Triple Fan 8GB VGA Card retail (SA750T-800C)"
   },
   {
    "shop": "amazon.fr",
    "price": 230.0,
    "currency": "EUR",
    "url": "https://www.gputracker.eu/si-click/1/3968434/asrock-tarjeta-grafica-arc-a750-challenger-se-8gb-",
    "inStock": true,
    "lastSeen": "2026-07-06T12:02:39Z",
    "product": "ASRock Tarjeta Gráfica Arc A750 Challenger SE 8GB GDDR6 Dual HDMI/DP OC"
   },
   {
    "shop": "jacob.de",
    "price": 232.0,
    "currency": "EUR",
    "url": "https://www.gputracker.eu/si-click/1/3675247/asrock-intel-arc-a750-challenger-se-8go-intel-vga-",
    "inStock": true,
    "lastSeen": "2026-07-06T12:02:39Z",
    "product": "ASROCK Intel ARC A750 Challenger SE 8GO Intel VGA Card retail"
   },
   {
    "shop": "bpm-power.com",
    "price": 234.0,
    "currency": "EUR",
    "url": "https://www.gputracker.eu/si-click/1/3304389/scheda-video-intel-sparkle-arc-a750-roc-luna-edizi",
    "inStock": true,
    "lastSeen": "2026-07-06T12:02:39Z",
    "product": "Scheda Video Intel Sparkle Arc A750 Roc Luna Edizione OC 8GB GDDR6 2xventole Bianco [SA750RW-8GOC]"
   },
   {
    "shop": "jacob.de",
    "price": 242.0,
    "currency": "EUR",
    "url": "https://www.gputracker.eu/si-click/1/3577900/sparkle-intel-arc-a750-orc-luna-oc-dual-fan-8gb-re",
    "inStock": true,
    "lastSeen": "2026-07-06T12:02:39Z",
    "product": "SPARKLE Intel ARC A750 ORC Luna OC Dual Fan 8GB retail (SA750RW-8GO)"
   }
  ],
  "image": "images/intel-arc-a750.png",
  "sourceUrl": "https://www.gputracker.eu/en/search/category/1/graphics-cards/facet/2/graphics-chip/intel-arc-a750",
  "lastUpdated": "2026-07-06T12:02:39Z",
  "imageSource": "https://img-cdn-aws.gputracker.eu/fit-in/150x150/products/471/1342/4711342290115.png?signature=1d89b9e73f0b3ffcd75ab126a3e6ce665954a5d5663c63cae4d8ab3f729b61fd"
 },
 {
  "id": "intel-arc-b580",
  "brand": "Intel",
  "name": "INTEL ARC B580",
  "index": 59.6,
  "vramGb": 12,
  "price": 310.0,
  "tdp": 190,
  "priceMin": 310.0,
  "prices": [
   {
    "shop": "reichelt.de",
    "price": 310.0,
    "currency": "EUR",
    "url": "https://www.gputracker.eu/si-click/1/3699068/spark-sb580g-sparkle-intel-arc-b580-guardian-12-gb",
    "inStock": true,
    "lastSeen": "2026-07-06T12:02:39Z",
    "product": "SPARK SB580G - SPARKLE Intel Arc B580 GUARDIAN 12 GB"
   },
   {
    "shop": "codima.be",
    "price": 311.0,
    "currency": "EUR",
    "url": "https://www.gputracker.eu/si-click/1/4265239/sparkle-intel-arc-b580-titan-luna-oc-12gb",
    "inStock": false,
    "lastSeen": "2026-07-06T12:02:39Z",
    "product": "Sparkle Intel Arc B580 TITAN Luna OC 12GB"
   },
   {
    "shop": "reichelt.de",
    "price": 320.0,
    "currency": "EUR",
    "url": "https://www.gputracker.eu/si-click/1/3699070/asr-90ga5lzz-asrock-intel-arc-b580-challenger-12-g",
    "inStock": true,
    "lastSeen": "2026-07-06T12:02:39Z",
    "product": "ASR 90GA5LZZ - ASRock Intel Arc B580 Challenger 12 GB OC"
   },
   {
    "shop": "alternate.fr",
    "price": 322.0,
    "currency": "EUR",
    "url": "https://www.gputracker.eu/si-click/1/3507466/asrock-intel-arc-b580-challenger-12go-oc-carte-gra",
    "inStock": true,
    "lastSeen": "2026-07-06T12:02:39Z",
    "product": "ASRock Intel® Arc B580 Challenger 12Go OC, Carte graphique"
   },
   {
    "shop": "bpm-power.com",
    "price": 328.0,
    "currency": "EUR",
    "url": "https://www.gputracker.eu/si-click/1/3696503/scheda-video-intel-sparkle-arc-b580-12gb-guardian-",
    "inStock": true,
    "lastSeen": "2026-07-06T12:02:39Z",
    "product": "Scheda Video Intel Sparkle ARC B580 12GB GUARDIAN (Battlemage Lineup) [SB580G-12G]"
   },
   {
    "shop": "jacob.de",
    "price": 330.0,
    "currency": "EUR",
    "url": "https://www.gputracker.eu/si-click/1/3693912/sparkle-vga-sparkle-intel-arc-b580-12gb-guardian-b",
    "inStock": true,
    "lastSeen": "2026-07-06T12:02:39Z",
    "product": "SPARKLE VGA SPARKLE Intel ARC B580 12GB GUARDIAN (Battlemage Lineup) (SB580G-12G)"
   },
   {
    "shop": "codima.be",
    "price": 330.0,
    "currency": "EUR",
    "url": "https://www.gputracker.eu/si-click/1/4265244/asrock-intel-arc-b580-steel-legend-12gb-oc",
    "inStock": false,
    "lastSeen": "2026-07-06T12:02:39Z",
    "product": "ASRock Intel Arc B580 Steel Legend 12GB OC"
   },
   {
    "shop": "amazon.fr",
    "price": 333.0,
    "currency": "EUR",
    "url": "https://www.gputracker.eu/si-click/1/3853278/asrock-intel-arc-b580-challenger-12go-intel-vga-ca",
    "inStock": true,
    "lastSeen": "2026-07-06T12:02:39Z",
    "product": "ASRock Intel Arc B580 Challenger 12GO Intel VGA Card"
   },
   {
    "shop": "jacob.de",
    "price": 355.0,
    "currency": "EUR",
    "url": "https://www.gputracker.eu/si-click/1/4202627/asrock-challenger-intel-arc-b580-12gb-oc-b580-cl-1",
    "inStock": true,
    "lastSeen": "2026-07-06T12:02:39Z",
    "product": "ASRock Challenger Intel Arc B580 12GB OC (B580 CL 12GO)"
   },
   {
    "shop": "topbiz.fr",
    "price": 358.0,
    "currency": "EUR",
    "url": "https://www.gputracker.eu/si-click/1/3619763/asrock-intel-arc-b580-challenger-12gb-oc-12-go-gdd",
    "inStock": true,
    "lastSeen": "2026-07-06T12:02:39Z",
    "product": "Asrock Intel Arc B580 Challenger 12GB OC 12 Go GDDR6"
   },
   {
    "shop": "reichelt.de",
    "price": 359.0,
    "currency": "EUR",
    "url": "https://www.gputracker.eu/si-click/1/3699075/asr-90ga5czz-asrock-intel-arc-b580-steel-legend-12",
    "inStock": true,
    "lastSeen": "2026-07-06T12:02:39Z",
    "product": "ASR 90GA5CZZ - ASRock Intel Arc B580 Steel Legend 12 GB OC"
   },
   {
    "shop": "amazon.fr",
    "price": 363.0,
    "currency": "EUR",
    "url": "https://www.gputracker.eu/si-click/1/4629418/intel-arc-b580-battlemage-limited-edition-12gb-gdd",
    "inStock": true,
    "lastSeen": "2026-07-06T12:02:39Z",
    "product": "Intel Arc B580 Battlemage Limited Edition 12GB GDDR6"
   },
   {
    "shop": "bpm-power.com",
    "price": 372.0,
    "currency": "EUR",
    "url": "https://www.gputracker.eu/si-click/1/3601480/scheda-video-intel-sparkle-intel-arc-b580-12gb-tit",
    "inStock": true,
    "lastSeen": "2026-07-06T12:02:39Z",
    "product": "Scheda Video Intel Sparkle Intel Arc B580 12GB Titan OC 2x ventola GDDR6 Blu [SB580T-12GOC]"
   },
   {
    "shop": "jacob.de",
    "price": 381.0,
    "currency": "EUR",
    "url": "https://www.gputracker.eu/si-click/1/3613486/sparkle-arc-b580-titan-oc-12gb-gddr6-sb580t-12goc",
    "inStock": true,
    "lastSeen": "2026-07-06T12:02:39Z",
    "product": "SPARKLE Arc B580 TITAN OC 12GB GDDR6 (SB580T-12GOC)"
   },
   {
    "shop": "amazon.fr",
    "price": 385.0,
    "currency": "EUR",
    "url": "https://www.gputracker.eu/si-click/1/4734970/weeliao-maxsun-intel-arc-b580-12g-icraft-carte-gra",
    "inStock": true,
    "lastSeen": "2026-07-06T12:02:39Z",
    "product": "WEELIAO MAXSUN Intel Arc B580 12G iCraft Carte graphique blanche, 2670 ~ 2850 MHz, 12 Go GDDR6, 192 bits, PCIE4.0, 1 HDMI2.1a, 3 DP2.1, 3 ventilateurs"
   },
   {
    "shop": "materiel.net",
    "price": 390.0,
    "currency": "EUR",
    "url": "https://www.gputracker.eu/si-click/1/3488998/asrock-intel-arc-b580-challenger-12gb-oc",
    "inStock": false,
    "lastSeen": "2026-07-06T12:02:39Z",
    "product": "ASRock Intel Arc B580 Challenger 12GB OC"
   },
   {
    "shop": "ldlc.com",
    "price": 390.0,
    "currency": "EUR",
    "url": "https://www.gputracker.eu/si-click/1/3488532/asrock-intel-arc-b580-challenger-12gb-oc",
    "inStock": false,
    "lastSeen": "2026-07-06T12:02:39Z",
    "product": "ASRock Intel Arc B580 Challenger 12GB OC"
   },
   {
    "shop": "amazon.fr",
    "price": 408.0,
    "currency": "EUR",
    "url": "https://www.gputracker.eu/si-click/1/3820602/sparkle-technology-intel-arc-b580-titan-oc-12-gb-g",
    "inStock": true,
    "lastSeen": "2026-07-06T12:02:39Z",
    "product": "Sparkle Technology Intel Arc B580 Titan Oc 12 Gb Gddr6 (sparkle Arc B580 Titan Oc 12gb Gddr6)"
   },
   {
    "shop": "amazon.fr",
    "price": 485.0,
    "currency": "EUR",
    "url": "https://www.gputracker.eu/si-click/1/3810431/asrock-cartegraphique-intelarcb580steellegendoc12g",
    "inStock": true,
    "lastSeen": "2026-07-06T12:02:39Z",
    "product": "ASRock Carte+Graphique Intel+Arc+B580+Steel+Legend+OC+12Go"
   },
   {
    "shop": "jacob.de",
    "price": 657.0,
    "currency": "EUR",
    "url": "https://www.gputracker.eu/si-click/1/3563796/acer-nitro-arc-b580-oc-grafikkarte-12gb-gddr6-hdmi",
    "inStock": true,
    "lastSeen": "2026-07-06T12:02:39Z",
    "product": "Acer Nitro Arc B580 OC Grafikkarte - 12GB GDDR6, HDMI, DP, 2x DP (DP.Z4BWW.P01)"
   }
  ],
  "image": "images/intel-arc-b580.png",
  "sourceUrl": "https://www.gputracker.eu/en/search/category/1/graphics-cards/facet/2/graphics-chip/intel-arc-b580",
  "lastUpdated": "2026-07-06T12:02:39Z",
  "imageSource": "https://img-cdn-aws.gputracker.eu/fit-in/150x150/products/471/1342/4711342290924.png?signature=b58cd78d7d976d7cf4a6a6901c83ebcb34f896bd0bc0d19b2b23befbb3937184"
 },
 {
  "id": "nvidia-rtx-4070-ti-super",
  "brand": "NVIDIA",
  "name": "NVIDIA  RTX 4070 TI SUPER",
  "index": 118.5,
  "vramGb": 16,
  "price": 807.0,
  "tdp": null,
  "priceMin": 807.0,
  "prices": [
   {
    "shop": "alternate.fr",
    "price": 807.0,
    "currency": "EUR",
    "url": "https://www.gputracker.eu/si-click/1/4184118/zotac-geforce-rtx-4070-ti-super-solid-reconditionn",
    "inStock": true,
    "lastSeen": "2026-07-06T12:02:39Z",
    "product": "ZOTAC GeForce RTX 4070 Ti SUPER SOLID Reconditionné, Carte graphique"
   },
   {
    "shop": "grosbill.com",
    "price": 833.0,
    "currency": "EUR",
    "url": "https://www.gputracker.eu/si-click/1/3665140/asus-geforce-rtx-4070-ti-super-dual-oc-16gb-second",
    "inStock": true,
    "lastSeen": "2026-07-06T12:02:39Z",
    "product": "Asus GeForce RTX 4070 TI SUPER Dual OC 16GB-Seconde Vie-Etat Satisfaisant"
   },
   {
    "shop": "cybertek.fr",
    "price": 849.0,
    "currency": "EUR",
    "url": "https://www.gputracker.eu/si-click/1/3200302/gigabyte-geforce-rtx-4070-ti-super-gaming-oc-16g-s",
    "inStock": true,
    "lastSeen": "2026-07-06T12:02:39Z",
    "product": "Gigabyte GeForce RTX 4070 Ti SUPER GAMING OC 16G-Seconde Vie-Etat Satisfaisant"
   },
   {
    "shop": "grosbill.com",
    "price": 850.0,
    "currency": "EUR",
    "url": "https://www.gputracker.eu/si-click/1/3200313/gigabyte-geforce-rtx-4070-ti-super-gaming-oc-16g-s",
    "inStock": true,
    "lastSeen": "2026-07-06T12:02:39Z",
    "product": "Gigabyte GeForce RTX 4070 Ti SUPER GAMING OC 16G-Seconde Vie-Etat Satisfaisant"
   },
   {
    "shop": "cybertek.fr",
    "price": 850.0,
    "currency": "EUR",
    "url": "https://www.gputracker.eu/si-click/1/3664984/asus-geforce-rtx-4070-ti-super-dual-oc-16gb-second",
    "inStock": true,
    "lastSeen": "2026-07-06T12:02:39Z",
    "product": "Asus GeForce RTX 4070 TI SUPER Dual OC 16GB-Seconde Vie-Etat Satisfaisant"
   },
   {
    "shop": "alternate.fr",
    "price": 908.0,
    "currency": "EUR",
    "url": "https://www.gputracker.eu/si-click/1/4195076/gainward-geforce-rtx-4070-ti-super-panther-oc-reco",
    "inStock": true,
    "lastSeen": "2026-07-06T12:02:39Z",
    "product": "Gainward GeForce RTX 4070 Ti SUPER Panther OC Reconditionné, Carte graphique"
   }
  ],
  "image": null,
  "sourceUrl": "https://www.gputracker.eu/en/search/category/1/graphics-cards/facet/2/graphics-chip/nvidia--rtx-4070-ti-super",
  "lastUpdated": "2026-07-06T12:02:39Z"
 },
 {
  "id": "nvidia-gt1030",
  "brand": "NVIDIA",
  "name": "NVIDIA GT1030",
  "index": 8.9,
  "vramGb": 2,
  "price": 73.0,
  "tdp": 30,
  "priceMin": 73.0,
  "prices": [
   {
    "shop": "jacob.de",
    "price": 73.0,
    "currency": "EUR",
    "url": "https://www.gputracker.eu/si-click/1/4692069/msi-gc-v809-2825r-geforce-gt1030-2ghd4-lp-oc-retai",
    "inStock": true,
    "lastSeen": "2026-07-06T12:02:39Z",
    "product": "MSI GC V809-2825R GeForce GT1030 2GHD4 LP OC Retail (V809-2825R) (B-Ware)"
   },
   {
    "shop": "cdiscount.com",
    "price": 75.0,
    "currency": "EUR",
    "url": "https://www.gputracker.eu/si-click/1/4702617/carte-graphique-msi-geforce-gt-1030-4-go-gddr4-pci",
    "inStock": true,
    "lastSeen": "2026-07-06T12:02:39Z",
    "product": "Carte graphique - MSI - GeForce GT 1030 - 4 Go GDDR4 - PCI Express 3.0 - Refroidissement actif"
   },
   {
    "shop": "bpm-power.com",
    "price": 77.0,
    "currency": "EUR",
    "url": "https://www.gputracker.eu/si-click/1/265609/scheda-video-nvidia-inno3d-gt1030-2gb-pci-edvihdmi",
    "inStock": true,
    "lastSeen": "2026-07-06T12:02:39Z",
    "product": "Scheda Video nVidia Inno3D GT1030 2GB PCI-E,DVI,HDMI,passiva [N1030-1SDV-E5BL]"
   },
   {
    "shop": "cdiscount.com",
    "price": 80.0,
    "currency": "EUR",
    "url": "https://www.gputracker.eu/si-click/1/4724822/carte-graphique-msi-geforce-gt-1030-4-go-gddr4-pci",
    "inStock": true,
    "lastSeen": "2026-07-06T12:02:39Z",
    "product": "Carte graphique - MSI - GeForce GT 1030 - 4 Go GDDR4 - PCI Express 3.0 - Refroidissement actif"
   },
   {
    "shop": "jacob.de",
    "price": 82.0,
    "currency": "EUR",
    "url": "https://www.gputracker.eu/si-click/1/2288074/innovision-inno3d-geforce-gt-1030-0db-n1030-1sdv-e",
    "inStock": true,
    "lastSeen": "2026-07-06T12:02:39Z",
    "product": "InnoVISION Inno3D GeForce GT 1030 0dB (N1030-1SDV-E5BL)"
   },
   {
    "shop": "amazon.de",
    "price": 82.0,
    "currency": "EUR",
    "url": "https://www.gputracker.eu/si-click/1/211863/asus-gt1030-sl-2g-brk-geforce-gt-1030-2-gb-gddr5-l",
    "inStock": true,
    "lastSeen": "2026-07-06T12:02:39Z",
    "product": "ASUS GT1030-SL-2G-BRK GeForce GT 1030 2 GB GDDR5 Low Profile Graphics Card for Silent HTPC Build (with I/O Port Brackets) - Black"
   },
   {
    "shop": "amazon.de",
    "price": 85.0,
    "currency": "EUR",
    "url": "https://www.gputracker.eu/si-click/1/288756/asus-geforce-gt-1030-2g-2-gb-gddr5-graphics-card-b",
    "inStock": true,
    "lastSeen": "2026-07-06T12:02:39Z",
    "product": "ASUS GeForce GT 1030 2G 2 GB GDDR5 Graphics Card - Black"
   },
   {
    "shop": "alternate.fr",
    "price": 87.0,
    "currency": "EUR",
    "url": "https://www.gputracker.eu/si-click/1/59691/inno3d-geforce-gt1030-heatsink-carte-graphique",
    "inStock": true,
    "lastSeen": "2026-07-06T12:02:39Z",
    "product": "INNO3D GeForce GT1030 Heatsink, Carte graphique"
   },
   {
    "shop": "amazon.fr",
    "price": 87.0,
    "currency": "EUR",
    "url": "https://www.gputracker.eu/si-click/1/3581768/msi-nvidia-geforce-gt-1030-4ghd4-lp-oc-carte-graph",
    "inStock": true,
    "lastSeen": "2026-07-06T12:02:39Z",
    "product": "MSI NVIDIA GeForce GT 1030 4GHD4 LP OC Carte Graphique - 4 Go GDDR4, 1430 MHz, PCIe, Conception Low Profile, DisplayPort, HDMI, système de Refroidi..."
   },
   {
    "shop": "reichelt.de",
    "price": 88.0,
    "currency": "EUR",
    "url": "https://www.gputracker.eu/si-click/1/2583708/msi-v809-2825r-msi-geforce-gt-1030-2ghd4-lp-oc",
    "inStock": false,
    "lastSeen": "2026-07-06T12:02:39Z",
    "product": "MSI V809-2825R - MSI GeForce GT 1030 2GHD4 LP OC"
   },
   {
    "shop": "bpm-power.com",
    "price": 89.0,
    "currency": "EUR",
    "url": "https://www.gputracker.eu/si-click/1/268963/scheda-video-nvidia-asus-gt-1030-2gb-gddr5-sl-brk-",
    "inStock": true,
    "lastSeen": "2026-07-06T12:02:39Z",
    "product": "Scheda Video nVidia Asus GT 1030 2GB GDDR5 SL BRK [90YV0AT0-M0NA00]"
   },
   {
    "shop": "compumsa.eu",
    "price": 90.0,
    "currency": "EUR",
    "url": "https://www.gputracker.eu/si-click/1/768521/asus-geforce-gt-1030-2gb-low-profile-gt1030-sl-2g-",
    "inStock": false,
    "lastSeen": "2026-07-06T12:02:39Z",
    "product": "Asus GeForce GT 1030 2GB Low Profile - GT1030-SL-2G-BRK - Carte graphique Nvidia"
   },
   {
    "shop": "cdiscount.com",
    "price": 90.0,
    "currency": "EUR",
    "url": "https://www.gputracker.eu/si-click/1/4515920/inno3d-carte-graphique-nvidia-geforce-gt-1030-pass",
    "inStock": true,
    "lastSeen": "2026-07-06T12:02:39Z",
    "product": "INNO3D - Carte Graphique - NVIDIA GeForce GT 1030 Passive - 2 Go"
   },
   {
    "shop": "bpm-power.com",
    "price": 90.0,
    "currency": "EUR",
    "url": "https://www.gputracker.eu/si-click/1/254544/scheda-video-nvidia-msi-geforce-gt-1030-2gb-2ghd4-",
    "inStock": true,
    "lastSeen": "2026-07-06T12:02:39Z",
    "product": "Scheda Video nVidia Msi GeForce GT 1030 2GB 2GHD4 LP OC [V809-2825R]"
   },
   {
    "shop": "bpm-power.com",
    "price": 91.0,
    "currency": "EUR",
    "url": "https://www.gputracker.eu/si-click/1/273319/scheda-video-nvidia-zotac-gt-1030-2gb-gddr5-hdcp-h",
    "inStock": true,
    "lastSeen": "2026-07-06T12:02:39Z",
    "product": "Scheda Video nVidia Zotac GT 1030 2GB GDDR5 HDCP HDMI DVI-D [ZT-P10300A-10L]"
   },
   {
    "shop": "topbiz.fr",
    "price": 91.0,
    "currency": "EUR",
    "url": "https://www.gputracker.eu/si-click/1/3609969/inno3d-n1030-1sdv-e5bl-carte-graphique-nvidia-gefo",
    "inStock": true,
    "lastSeen": "2026-07-06T12:02:39Z",
    "product": "Inno3D N1030-1SDV-E5BL carte graphique NVIDIA GeForce GT 1030 2 Go GDDR5"
   },
   {
    "shop": "bpm-power.com",
    "price": 92.0,
    "currency": "EUR",
    "url": "https://www.gputracker.eu/si-click/1/252479/scheda-video-nvidia-asus-gt1030-2g-brk-2gb-dp-hdmi",
    "inStock": true,
    "lastSeen": "2026-07-06T12:02:39Z",
    "product": "Scheda Video nVidia Asus GT1030-2G-BRK 2GB, Dp Hdmi [90YV0AT2-M0NA00]"
   },
   {
    "shop": "amazon.fr",
    "price": 95.0,
    "currency": "EUR",
    "url": "https://www.gputracker.eu/si-click/1/60646/asus-geforce-carte-graphique-gt-1030-2-go-gddr5-a-",
    "inStock": true,
    "lastSeen": "2026-07-06T12:02:39Z",
    "product": "ASUS GeForce Carte graphique GT 1030 2 Go GDDR5 à profil bas pour une construction HTPC silencieuse (avec supports de port d'E/S) Petite"
   },
   {
    "shop": "codima.be",
    "price": 95.0,
    "currency": "EUR",
    "url": "https://www.gputracker.eu/si-click/1/4265216/inno3d-geforce-gt-1030-silent-2gb-gddr5",
    "inStock": true,
    "lastSeen": "2026-07-06T12:02:39Z",
    "product": "Inno3D GeForce GT 1030 Silent 2GB GDDR5"
   }
  ],
  "image": "images/nvidia-gt1030.png",
  "sourceUrl": "https://www.gputracker.eu/en/search/category/1/graphics-cards/facet/2/graphics-chip/nvidia-gt1030",
  "lastUpdated": "2026-07-06T12:02:39Z",
  "imageSource": "https://img-cdn-aws.gputracker.eu/fit-in/150x150/products/471/9072/4719072561420.png?signature=532915e9d4fecd47157fbe04a9151771e9747ad0bc4e2c0f7e5db09259977494"
 },
 {
  "id": "nvidia-gt710",
  "brand": "NVIDIA",
  "name": "NVIDIA GT710",
  "index": 2.3,
  "vramGb": 2,
  "price": 55.0,
  "tdp": 19,
  "priceMin": 55.0,
  "prices": [
   {
    "shop": "bpm-power.com",
    "price": 55.0,
    "currency": "EUR",
    "url": "https://www.gputracker.eu/si-click/1/269072/scheda-video-nvidia-inno3d-gt710-2gb-sddr3-64bit-h",
    "inStock": true,
    "lastSeen": "2026-07-06T12:02:39Z",
    "product": "Scheda Video nVidia Inno3D GT710 2GB SDDR3 64bit, HDMI, DVI, PCI-E con CUDA, passiva [N710-1SDV-E3BX]"
   }
  ],
  "image": "images/nvidia-gt710.png",
  "sourceUrl": "https://www.gputracker.eu/en/search/category/1/graphics-cards/facet/2/graphics-chip/nvidia-gt710",
  "lastUpdated": "2026-07-06T12:02:39Z"
 },
 {
  "id": "nvidia-gt730",
  "brand": "NVIDIA",
  "name": "NVIDIA GT730",
  "index": 3.1,
  "vramGb": 2,
  "price": 64.0,
  "tdp": null,
  "priceMin": 64.0,
  "prices": [
   {
    "shop": "amazon.de",
    "price": 64.0,
    "currency": "EUR",
    "url": "https://www.gputracker.eu/si-click/1/210659/asus-geforce-gt-730-2-gb-gddr5-low-profile-graphic",
    "inStock": true,
    "lastSeen": "2026-07-06T12:02:39Z",
    "product": "ASUS GeForce GT 730 2 GB GDDR5 Low Profile Graphics Card for Silent HTPC Build (with I/O Port Brackets) GT730-SL-2GD5-BRK"
   }
  ],
  "image": "images/nvidia-gt730.png",
  "sourceUrl": "https://www.gputracker.eu/en/search/category/1/graphics-cards/facet/2/graphics-chip/nvidia-gt730",
  "lastUpdated": "2026-07-06T12:02:39Z"
 },
 {
  "id": "nvidia-rtx-2000",
  "brand": "NVIDIA",
  "name": "NVIDIA RTX 2000",
  "index": 63.1,
  "vramGb": 16,
  "price": 661.0,
  "tdp": 70,
  "priceMin": 661.0,
  "prices": [
   {
    "shop": "bpm-power.com",
    "price": 661.0,
    "currency": "EUR",
    "url": "https://www.gputracker.eu/si-click/1/3931313/scheda-video-nvidia-pny-rtx2000-ada-lovelace-16gb-",
    "inStock": true,
    "lastSeen": "2026-07-06T12:02:39Z",
    "product": "Scheda Video nVidia Pny RTX2000 Ada Lovelace 16GB GDDR6 128bit Nero [VCNRTX2000ADA-SB]"
   }
  ],
  "image": "images/nvidia-rtx-2000.png",
  "sourceUrl": "https://www.gputracker.eu/en/search/category/1/graphics-cards/facet/2/graphics-chip/nvidia-rtx-2000",
  "lastUpdated": "2026-07-06T12:02:39Z"
 },
 {
  "id": "nvidia-rtx-3050",
  "brand": "NVIDIA",
  "name": "NVIDIA RTX 3050",
  "index": 46.4,
  "vramGb": null,
  "price": 180.0,
  "tdp": 130,
  "priceMin": 180.0,
  "prices": [
   {
    "shop": "grosbill.com",
    "price": 180.0,
    "currency": "EUR",
    "url": "https://www.gputracker.eu/si-click/1/3131145/asus-dual-rtx3050-o6g",
    "inStock": true,
    "lastSeen": "2026-07-06T12:02:39Z",
    "product": "Asus DUAL-RTX3050-O6G"
   }
  ],
  "image": "images/nvidia-rtx-3050.png",
  "sourceUrl": "https://www.gputracker.eu/en/search/category/1/graphics-cards/facet/2/graphics-chip/nvidia-rtx-3050",
  "lastUpdated": "2026-07-06T12:02:39Z"
 },
 {
  "id": "nvidia-rtx-3060",
  "brand": "NVIDIA",
  "name": "NVIDIA RTX 3060",
  "index": 62.8,
  "vramGb": null,
  "price": 298.0,
  "tdp": 170,
  "priceMin": 298.0,
  "prices": [
   {
    "shop": "alternate.fr",
    "price": 298.0,
    "currency": "EUR",
    "url": "https://www.gputracker.eu/si-click/1/4480803/zotac-geforce-rtx-3060-twin-edge-reconditionne-car",
    "inStock": true,
    "lastSeen": "2026-07-06T12:02:39Z",
    "product": "ZOTAC GeForce RTX 3060 Twin Edge reconditionné, Carte graphique"
   }
  ],
  "image": "images/nvidia-rtx-3060.png",
  "sourceUrl": "https://www.gputracker.eu/en/search/category/1/graphics-cards/facet/2/graphics-chip/nvidia-rtx-3060",
  "lastUpdated": "2026-07-06T12:02:39Z"
 },
 {
  "id": "nvidia-rtx-3060-ti",
  "brand": "NVIDIA",
  "name": "NVIDIA RTX 3060 TI",
  "index": 75.3,
  "vramGb": null,
  "price": 395.0,
  "tdp": 200,
  "priceMin": 395.0,
  "prices": [
   {
    "shop": "alternate.fr",
    "price": 395.0,
    "currency": "EUR",
    "url": "https://www.gputracker.eu/si-click/1/4690904/zotac-geforce-rtx-3060-ti-twin-edge-lhr-reconditio",
    "inStock": true,
    "lastSeen": "2026-07-06T12:02:39Z",
    "product": "ZOTAC GeForce RTX 3060 Ti Twin Edge LHR reconditionné, Carte graphique"
   }
  ],
  "image": "images/nvidia-rtx-3060-ti.png",
  "sourceUrl": "https://www.gputracker.eu/en/search/category/1/graphics-cards/facet/2/graphics-chip/nvidia-rtx-3060-ti",
  "lastUpdated": "2026-07-06T12:02:39Z"
 },
 {
  "id": "nvidia-rtx-3070",
  "brand": "NVIDIA",
  "name": "NVIDIA RTX 3070",
  "index": 82.2,
  "vramGb": null,
  "price": 425.0,
  "tdp": 220,
  "priceMin": 425.0,
  "prices": [
   {
    "shop": "grosbill.com",
    "price": 425.0,
    "currency": "EUR",
    "url": "https://www.gputracker.eu/si-click/1/4591282/gigabyte-geforce-rtx-3070-gaming-oc-8g-lhr-seconde",
    "inStock": true,
    "lastSeen": "2026-07-06T12:02:39Z",
    "product": "Gigabyte GeForce RTX 3070 GAMING OC 8G LHR-Seconde Vie-Etat Satisfaisant"
   }
  ],
  "image": "images/nvidia-rtx-3070.png",
  "sourceUrl": "https://www.gputracker.eu/en/search/category/1/graphics-cards/facet/2/graphics-chip/nvidia-rtx-3070",
  "lastUpdated": "2026-07-06T12:02:39Z"
 },
 {
  "id": "nvidia-rtx-3070-ti",
  "brand": "NVIDIA",
  "name": "NVIDIA RTX 3070 TI",
  "index": 86.3,
  "vramGb": 8,
  "price": 350.0,
  "tdp": 290,
  "priceMin": 350.0,
  "prices": [
   {
    "shop": "grosbill.com",
    "price": 350.0,
    "currency": "EUR",
    "url": "https://www.gputracker.eu/si-click/1/3242856/carte-graphique-rtx-3070ti-8gb-seconde-vie-etat-sa",
    "inStock": true,
    "lastSeen": "2026-07-06T12:02:39Z",
    "product": "Carte graphique RTX 3070Ti 8GB-Seconde Vie-Etat Satisfaisant"
   }
  ],
  "image": "images/nvidia-rtx-3070-ti.png",
  "sourceUrl": "https://www.gputracker.eu/en/search/category/1/graphics-cards/facet/2/graphics-chip/nvidia-rtx-3070-ti",
  "lastUpdated": "2026-07-06T12:02:39Z"
 },
 {
  "id": "nvidia-rtx-4000",
  "brand": "NVIDIA",
  "name": "NVIDIA RTX 4000",
  "index": 88.0,
  "vramGb": 20,
  "price": 1479.0,
  "tdp": 130,
  "priceMin": 1479.0,
  "prices": [
   {
    "shop": "alternate.fr",
    "price": 1479.0,
    "currency": "EUR",
    "url": "https://www.gputracker.eu/si-click/1/3277491/pny-nvidia-rtx-4000-ada-generation-20gb-sb-carte-g",
    "inStock": true,
    "lastSeen": "2026-07-06T12:02:39Z",
    "product": "PNY NVIDIA RTX 4000 Ada Generation 20GB SB, Carte graphique"
   }
  ],
  "image": "images/nvidia-rtx-4000.png",
  "sourceUrl": "https://www.gputracker.eu/en/search/category/1/graphics-cards/facet/2/graphics-chip/nvidia-rtx-4000",
  "lastUpdated": "2026-07-06T12:02:39Z"
 },
 {
  "id": "nvidia-rtx-4070",
  "brand": "NVIDIA",
  "name": "NVIDIA RTX 4070",
  "index": 100.0,
  "vramGb": 12,
  "price": 605.0,
  "tdp": 200,
  "priceMin": 605.0,
  "prices": [
   {
    "shop": "grosbill.com",
    "price": 605.0,
    "currency": "EUR",
    "url": "https://www.gputracker.eu/si-click/1/4721607/palit-rtx-4070-dual-12gb-gddr6x-dlss3-seconde-vie-",
    "inStock": true,
    "lastSeen": "2026-07-06T12:02:39Z",
    "product": "Palit RTX 4070 Dual 12GB GDDR6X - DLSS3-Seconde Vie-Très Bon Etat"
   }
  ],
  "image": null,
  "sourceUrl": "https://www.gputracker.eu/en/search/category/1/graphics-cards/facet/2/graphics-chip/nvidia-rtx-4070",
  "lastUpdated": "2026-07-06T12:02:39Z"
 },
 {
  "id": "nvidia-rtx-4070-ti",
  "brand": "NVIDIA",
  "name": "NVIDIA RTX 4070 TI",
  "index": 117.4,
  "vramGb": null,
  "price": 835.0,
  "tdp": 285,
  "priceMin": 835.0,
  "prices": [
   {
    "shop": "alternate.fr",
    "price": 835.0,
    "currency": "EUR",
    "url": "https://www.gputracker.eu/si-click/1/4184121/gainward-geforce-rtx-4070-ti-phoenix-reconditionne",
    "inStock": true,
    "lastSeen": "2026-07-06T12:02:39Z",
    "product": "Gainward GeForce RTX 4070 Ti Phoenix Reconditionné, Carte graphique"
   }
  ],
  "image": "images/nvidia-rtx-4070-ti.png",
  "sourceUrl": "https://www.gputracker.eu/en/search/category/1/graphics-cards/facet/2/graphics-chip/nvidia-rtx-4070-ti",
  "lastUpdated": "2026-07-06T12:02:39Z"
 },
 {
  "id": "nvidia-rtx-4080",
  "brand": "NVIDIA",
  "name": "NVIDIA RTX 4080",
  "index": 128.2,
  "vramGb": 16,
  "price": 952.0,
  "tdp": 320,
  "priceMin": 952.0,
  "prices": [
   {
    "shop": "grosbill.com",
    "price": 952.0,
    "currency": "EUR",
    "url": "https://www.gputracker.eu/si-click/1/4670199/gigabyte-geforce-rtx-4080-16gb-eagle-seconde-vie-b",
    "inStock": true,
    "lastSeen": "2026-07-06T12:02:39Z",
    "product": "Gigabyte GeForce RTX 4080 16GB EAGLE-Seconde Vie-Bon Etat"
   }
  ],
  "image": "images/nvidia-rtx-4080.png",
  "sourceUrl": "https://www.gputracker.eu/en/search/category/1/graphics-cards/facet/2/graphics-chip/nvidia-rtx-4080",
  "lastUpdated": "2026-07-06T12:02:39Z"
 },
 {
  "id": "nvidia-rtx-4080-super",
  "brand": "NVIDIA",
  "name": "NVIDIA RTX 4080 SUPER",
  "index": 127.4,
  "vramGb": null,
  "price": 1009.0,
  "tdp": 320,
  "priceMin": 1009.0,
  "prices": [
   {
    "shop": "alternate.fr",
    "price": 1009.0,
    "currency": "EUR",
    "url": "https://www.gputracker.eu/si-click/1/4480804/gainward-geforce-rtx-4080-super-phoenix-reconditio",
    "inStock": true,
    "lastSeen": "2026-07-06T12:02:39Z",
    "product": "Gainward GeForce RTX 4080 SUPER Phoenix Reconditionné, Carte graphique"
   }
  ],
  "image": null,
  "sourceUrl": "https://www.gputracker.eu/en/search/category/1/graphics-cards/facet/2/graphics-chip/nvidia-rtx-4080-super",
  "lastUpdated": "2026-07-06T12:02:39Z"
 },
 {
  "id": "nvidia-rtx-4500",
  "brand": "NVIDIA",
  "name": "NVIDIA RTX 4500",
  "index": 105.2,
  "vramGb": null,
  "price": 2261.0,
  "tdp": 210,
  "priceMin": 2261.0,
  "prices": [
   {
    "shop": "jacob.de",
    "price": 2261.0,
    "currency": "EUR",
    "url": "https://www.gputracker.eu/si-click/1/3108637/nvidia-rtx-4500-ada-900-5g132-2260-000",
    "inStock": true,
    "lastSeen": "2026-07-06T12:02:39Z",
    "product": "NVIDIA RTX 4500 ADA (900-5G132-2260-000)"
   }
  ],
  "image": "images/nvidia-rtx-4500.png",
  "sourceUrl": "https://www.gputracker.eu/en/search/category/1/graphics-cards/facet/2/graphics-chip/nvidia-rtx-4500",
  "lastUpdated": "2026-07-06T12:02:39Z"
 },
 {
  "id": "nvidia-rtx-5000",
  "brand": "NVIDIA",
  "name": "NVIDIA RTX 5000",
  "index": 113.6,
  "vramGb": 32,
  "price": 4502.0,
  "tdp": 250,
  "priceMin": 4502.0,
  "prices": [
   {
    "shop": "jacob.de",
    "price": 4502.0,
    "currency": "EUR",
    "url": "https://www.gputracker.eu/si-click/1/2828860/nvidia-rtx-5000-ada-generation-grafikkarte-32-gb-g",
    "inStock": true,
    "lastSeen": "2026-07-06T12:02:39Z",
    "product": "NVIDIA RTX 5000 Ada Generation Grafikkarte 32 GB GDDR6 PCIe 4.0 x16 4x DisplayPort (900-5G132-2240-000)"
   }
  ],
  "image": "images/nvidia-rtx-5000.png",
  "sourceUrl": "https://www.gputracker.eu/en/search/category/1/graphics-cards/facet/2/graphics-chip/nvidia-rtx-5000",
  "lastUpdated": "2026-07-06T12:02:39Z"
 },
 {
  "id": "nvidia-rtx-5050",
  "brand": "NVIDIA",
  "name": "NVIDIA RTX 5050",
  "index": 63.2,
  "vramGb": 8,
  "price": 252.0,
  "tdp": 130,
  "priceMin": 252.0,
  "prices": [
   {
    "shop": "grosbill.com",
    "price": 252.0,
    "currency": "EUR",
    "url": "https://www.gputracker.eu/si-click/1/4671728/asus-dual-geforce-rtx-5050-8gb-gddr6-oc-edition-se",
    "inStock": true,
    "lastSeen": "2026-07-06T12:02:39Z",
    "product": "Asus Dual GeForce RTX 5050 8GB GDDR6 OC Edition-Seconde Vie-Très Bon Etat"
   }
  ],
  "image": "images/nvidia-rtx-5050.png",
  "sourceUrl": "https://www.gputracker.eu/en/search/category/1/graphics-cards/facet/2/graphics-chip/nvidia-rtx-5050",
  "lastUpdated": "2026-07-06T12:02:39Z"
 },
 {
  "id": "nvidia-rtx-5060",
  "brand": "NVIDIA",
  "name": "NVIDIA RTX 5060",
  "index": 77.1,
  "vramGb": null,
  "price": 289.0,
  "tdp": 145,
  "priceMin": 289.0,
  "prices": [
   {
    "shop": "grosbill.com",
    "price": 289.0,
    "currency": "EUR",
    "url": "https://www.gputracker.eu/si-click/1/4718020/msi-geforce-rtx-5060-8g-shadow-2x-oc-oem-seconde-v",
    "inStock": true,
    "lastSeen": "2026-07-06T12:02:39Z",
    "product": "MSI GeForce RTX 5060 8G SHADOW 2X OC - OEM-Seconde Vie-Etat Satisfaisant"
   }
  ],
  "image": "images/nvidia-rtx-5060.png",
  "sourceUrl": "https://www.gputracker.eu/en/search/category/1/graphics-cards/facet/2/graphics-chip/nvidia-rtx-5060",
  "lastUpdated": "2026-07-06T12:02:39Z"
 },
 {
  "id": "nvidia-rtx-5060-ti",
  "brand": "NVIDIA",
  "name": "NVIDIA RTX 5060 TI",
  "index": 82.2,
  "vramGb": 8,
  "price": 320.0,
  "tdp": 180,
  "priceMin": 320.0,
  "prices": [
   {
    "shop": "grosbill.com",
    "price": 320.0,
    "currency": "EUR",
    "url": "https://www.gputracker.eu/si-click/1/3795290/asus-dual-geforce-rtx-5060-ti-8gb-gddr7-oc-edition",
    "inStock": true,
    "lastSeen": "2026-07-06T12:02:39Z",
    "product": "Asus Dual GeForce RTX 5060 Ti 8GB GDDR7 OC Edition"
   }
  ],
  "image": "images/nvidia-rtx-5060-ti.png",
  "sourceUrl": "https://www.gputracker.eu/en/search/category/1/graphics-cards/facet/2/graphics-chip/nvidia-rtx-5060-ti",
  "lastUpdated": "2026-07-06T12:02:39Z"
 },
 {
  "id": "nvidia-rtx-5070",
  "brand": "NVIDIA",
  "name": "NVIDIA RTX 5070",
  "index": 106.8,
  "vramGb": null,
  "price": 554.0,
  "tdp": 250,
  "priceMin": 554.0,
  "prices": [
   {
    "shop": "alternate.fr",
    "price": 554.0,
    "currency": "EUR",
    "url": "https://www.gputracker.eu/si-click/1/3773659/palit-geforce-rtx-5070-infinity-3-carte-graphique",
    "inStock": true,
    "lastSeen": "2026-07-06T12:02:39Z",
    "product": "Palit GeForce RTX 5070 Infinity 3, Carte graphique"
   }
  ],
  "image": "images/nvidia-rtx-5070.png",
  "sourceUrl": "https://www.gputracker.eu/en/search/category/1/graphics-cards/facet/2/graphics-chip/nvidia-rtx-5070",
  "lastUpdated": "2026-07-06T12:02:39Z"
 },
 {
  "id": "nvidia-rtx-5070-ti",
  "brand": "NVIDIA",
  "name": "NVIDIA RTX 5070 TI",
  "index": 120.4,
  "vramGb": null,
  "price": 841.0,
  "tdp": 300,
  "priceMin": 841.0,
  "prices": [
   {
    "shop": "grosbill.com",
    "price": 841.0,
    "currency": "EUR",
    "url": "https://www.gputracker.eu/si-click/1/4670198/inno3d-geforce-rtx-5070-ti-x3-oc-seconde-vie-etat-",
    "inStock": true,
    "lastSeen": "2026-07-06T12:02:39Z",
    "product": "Inno3D GeForce RTX 5070 Ti X3 OC-Seconde Vie-Etat Satisfaisant"
   }
  ],
  "image": "images/nvidia-rtx-5070-ti.png",
  "sourceUrl": "https://www.gputracker.eu/en/search/category/1/graphics-cards/facet/2/graphics-chip/nvidia-rtx-5070-ti",
  "lastUpdated": "2026-07-06T12:02:39Z"
 },
 {
  "id": "nvidia-rtx-5080",
  "brand": "NVIDIA",
  "name": "NVIDIA RTX 5080",
  "index": 132.7,
  "vramGb": null,
  "price": 1169.0,
  "tdp": 360,
  "priceMin": 1169.0,
  "prices": [
   {
    "shop": "alternate.fr",
    "price": 1169.0,
    "currency": "EUR",
    "url": "https://www.gputracker.eu/si-click/1/3878003/palit-geforce-rtx-5080-gamingpro-v1-carte-graphiqu",
    "inStock": true,
    "lastSeen": "2026-07-06T12:02:39Z",
    "product": "Palit GeForce RTX 5080 GamingPro V1, Carte graphique"
   }
  ],
  "image": "images/nvidia-rtx-5080.png",
  "sourceUrl": "https://www.gputracker.eu/en/search/category/1/graphics-cards/facet/2/graphics-chip/nvidia-rtx-5080",
  "lastUpdated": "2026-07-06T12:02:39Z"
 },
 {
  "id": "nvidia-rtx-5090",
  "brand": "NVIDIA",
  "name": "NVIDIA RTX 5090",
  "index": 144.9,
  "vramGb": 32,
  "price": 3246.0,
  "tdp": 575,
  "priceMin": 3246.0,
  "prices": [
   {
    "shop": "compumsa.eu",
    "price": 3246.0,
    "currency": "EUR",
    "url": "https://www.gputracker.eu/si-click/1/3761476/msi-geforce-rtx-5090-32gb-vanguard-soc-carte-graph",
    "inStock": true,
    "lastSeen": "2026-07-06T12:02:39Z",
    "product": "MSI GeForce RTX 5090 32GB Vanguard SOC - Carte graphique Nvidia"
   }
  ],
  "image": "images/nvidia-rtx-5090.png",
  "sourceUrl": "https://www.gputracker.eu/en/search/category/1/graphics-cards/facet/2/graphics-chip/nvidia-rtx-5090",
  "lastUpdated": "2026-07-06T12:02:39Z"
 },
 {
  "id": "nvidia-rtx-6000",
  "brand": "NVIDIA",
  "name": "NVIDIA RTX 6000",
  "index": 107.1,
  "vramGb": null,
  "price": 4322.0,
  "tdp": 300,
  "priceMin": 4322.0,
  "prices": [
   {
    "shop": "grosbill.com",
    "price": 4322.0,
    "currency": "EUR",
    "url": "https://www.gputracker.eu/si-click/1/1325297/pny-quadro-rtx-6000",
    "inStock": true,
    "lastSeen": "2026-07-06T12:02:39Z",
    "product": "PNY Quadro RTX 6000"
   }
  ],
  "image": "images/nvidia-rtx-6000.png",
  "sourceUrl": "https://www.gputracker.eu/en/search/category/1/graphics-cards/facet/2/graphics-chip/nvidia-rtx-6000",
  "lastUpdated": "2026-07-06T12:02:39Z"
 },
 {
  "id": "nvidia-rtx-a1000",
  "brand": "NVIDIA",
  "name": "NVIDIA RTX A1000",
  "index": 39.8,
  "vramGb": null,
  "price": 399.0,
  "tdp": 50,
  "priceMin": 399.0,
  "prices": [
   {
    "shop": "jacob.de",
    "price": 399.0,
    "currency": "EUR",
    "url": "https://www.gputracker.eu/si-click/1/3226864/nvidia-rtx-a1000-grafikkarten-900-5g172-2280-000",
    "inStock": true,
    "lastSeen": "2026-07-06T12:02:39Z",
    "product": "NVIDIA RTX A1000 - Grafikkarten (900-5G172-2280-000)"
   }
  ],
  "image": "images/nvidia-rtx-a1000.png",
  "sourceUrl": "https://www.gputracker.eu/en/search/category/1/graphics-cards/facet/2/graphics-chip/nvidia-rtx-a1000",
  "lastUpdated": "2026-07-06T12:02:39Z"
 }
]